pyridescence.cpython-310-aarch64-linux-gnu.so
pyridescence.libs/libOpenGL-390f9cb8.so.0.0.0
pyridescence.libs/libGLX-f54d12ee.so.0.0.0
pyridescence.libs/libGLdispatch-7af6d45b.so.0.0.0
pyridescence.libs/libpng16-11aed5ca.so.16.34.0
pyridescence.libs/libjpeg-ee25248c.so.62.2.0
pyridescence-1.0.1.dist-info/WHEEL
pyridescence-1.0.1.dist-info/top_level.txt
pyridescence-1.0.1.dist-info/METADATA
pyridescence-1.0.1.dist-info/RECORD
pyridescence-1.0.1.dist-info/licenses/LICENSE
lib64/libiridescence.a
lib64/libglfw3.a
lib64/pkgconfig/glfw3.pc
lib64/cmake/iridescence/iridescence-targets.cmake
lib64/cmake/iridescence/iridescence-config.cmake
lib64/cmake/iridescence/iridescence-targets-release.cmake
lib64/cmake/iridescence/iridescence-config-version.cmake
lib64/cmake/glfw3/glfw3Targets-release.cmake
lib64/cmake/glfw3/glfw3ConfigVersion.cmake
lib64/cmake/glfw3/glfw3Config.cmake
lib64/cmake/glfw3/glfw3Targets.cmake
pyridescence/__init__.pyi
pyridescence/guik.pyi
pyridescence/pfd.pyi
pyridescence/gl.pyi
pyridescence/imgui.pyi
pyridescence/glk/__init__.pyi
pyridescence/glk/primitives.pyi
pyridescence_data/__init__.py
pyridescence_data/models/bunny.ply
pyridescence_data/shader/transform_normal_dists_indices.comp
pyridescence_data/shader/splatting.vert
pyridescence_data/shader/splatting.geom
pyridescence_data/shader/ssae_ao.frag
pyridescence_data/shader/phong.vert
pyridescence_data/shader/ssae_normal.frag
pyridescence_data/shader/rainbow.vert
pyridescence_data/shader/transform_normal_dists_vertices.comp
pyridescence_data/shader/phong.frag
pyridescence_data/shader/naive_ssao.frag
pyridescence_data/shader/ssao.frag
pyridescence_data/shader/bilateral.frag
pyridescence_data/shader/ssae_pos.frag
pyridescence_data/shader/rainbow.frag
pyridescence_data/shader/ssli.frag
pyridescence_data/shader/partial_clear.frag
pyridescence_data/shader/splatting.frag
pyridescence_data/shader/texture.vert
pyridescence_data/shader/iridescence.frag
pyridescence_data/shader/texture.frag
pyridescence_data/shader/brdf/specular_phong.frag
pyridescence_data/shader/brdf/diffuse_disney_normalized.frag
pyridescence_data/shader/brdf/diffuse_one.frag
