Metadata-Version: 2.4
Name: pyridescence
Version: 1.0.1
Summary: 3D visualization library for rapid prototyping of 3D algorithms
Author: Kenji Koide
Author-email: k.koide@aist.go.jp
License: MIT
Requires-Python: >=3.7
License-File: LICENSE
Requires-Dist: numpy
Dynamic: author
Dynamic: author-email
Dynamic: description
Dynamic: description-content-type
Dynamic: license
Dynamic: license-file
Dynamic: requires-dist
Dynamic: requires-python
Dynamic: summary
